audioldm_eval/__init__.py
audioldm_eval/eval.py
audioldm_eval/audio/__init__.py
audioldm_eval/audio/audio_processing.py
audioldm_eval/audio/stft.py
audioldm_eval/audio/tools.py
audioldm_eval/datasets/__init__.py
audioldm_eval/datasets/load_mel.py
audioldm_eval/datasets/transforms.py
audioldm_eval/feature_extractors/__init__.py
audioldm_eval/feature_extractors/inception3.py
audioldm_eval/feature_extractors/melception.py
audioldm_eval/feature_extractors/melception_audioset.py
audioldm_eval/feature_extractors/panns/__init__.py
audioldm_eval/feature_extractors/panns/config.py
audioldm_eval/feature_extractors/panns/evaluate.py
audioldm_eval/feature_extractors/panns/finetune_template.py
audioldm_eval/feature_extractors/panns/losses.py
audioldm_eval/feature_extractors/panns/main.py
audioldm_eval/feature_extractors/panns/models.py
audioldm_eval/feature_extractors/panns/pytorch_utils.py
audioldm_eval/feature_extractors/panns/utilities.py
audioldm_eval/metrics/__init__.py
audioldm_eval/metrics/fad.py
audioldm_eval/metrics/fid.py
audioldm_eval/metrics/isc.py
audioldm_eval/metrics/kid.py
audioldm_eval/metrics/kl.py
audioldm_eval/metrics/ndb.py
audioldm_eval/metrics/validate.py
audioldm_eval/metrics/gs/__init__.py
audioldm_eval/metrics/gs/geom_score.py
audioldm_eval/metrics/gs/top_utils.py
audioldm_eval/metrics/gs/utils.py
audioldm_eval-0.0.3.dist-info/LICENSE
audioldm_eval-0.0.3.dist-info/METADATA
audioldm_eval-0.0.3.dist-info/WHEEL
audioldm_eval-0.0.3.dist-info/top_level.txt
audioldm_eval-0.0.3.dist-info/RECORD
