Metadata-Version: 2.1
Name: audioldm-eval
Version: 0.0.3
Summary: This package is written for the evaluation of audio generation model.
Home-page: https://github.com/haoheliu/audioldm_eval
Author: Haohe Liu
Author-email: haoheliu@gmail.com
License: MIT
Classifier: License :: OSI Approved :: MIT License
Classifier: Programming Language :: Python
Classifier: Programming Language :: Python :: 3
Classifier: Programming Language :: Python :: 3.7
Classifier: Programming Language :: Python :: Implementation :: CPython
Classifier: Programming Language :: Python :: Implementation :: PyPy
Requires-Python: >=3.6.0
License-File: LICENSE
Requires-Dist: torch (>=1.11.0)
Requires-Dist: torchaudio
Requires-Dist: scikit-image
Requires-Dist: torchlibrosa
Requires-Dist: absl-py
Requires-Dist: scipy
Requires-Dist: tqdm
Requires-Dist: ssr-eval
Requires-Dist: librosa
